{
  "timestamp": "2025-10-31T22:23:32Z",
  "stage": "embed",
  "source": "forsgren_n.,_humble_j.,_kim_g.-_accelerate._the_science_of_devops_-_2018.dataset.chunks.jsonl",
  "metrics": {
    "total_vectors": 271,
    "embedding_dim": 384,
    "embedding_failures": 0,
    "failure_rate": 0.0,
    "avg_norm": 1.0,
    "min_norm": 0.9999999403953552,
    "max_norm": 1.0000001192092896
  },
  "threshold_check": {
    "passed": true,
    "violations": [],
    "warnings": [
      "Missing metric: min_embedding_success",
      "Missing metric: max_embedding_time_per_chunk"
    ]
  }
}